generals/__init__.py
generals/agents/__init__.py
generals/agents/agent.py
generals/agents/agent_factory.py
generals/agents/expander_agent.py
generals/agents/random_agent.py
generals/assets/__init__.py
generals/assets/fonts/__init__.py
generals/assets/images/__init__.py
generals/core/__init__.py
generals/core/channels.py
generals/core/config.py
generals/core/game.py
generals/core/grid.py
generals/core/replay.py
generals/envs/__init__.py
generals/envs/gymnasium_generals.py
generals/envs/gymnasium_wrappers.py
generals/envs/initializers.py
generals/envs/pettingzoo_generals.py
generals/gui/__init__.py
generals/gui/event_handler.py
generals/gui/gui.py
generals/gui/properties.py
generals/gui/rendering.py
tests/__init__.py
tests/parallel_api_check.py
tests/test_game.py
tests/test_gym.py
tests/test_map.py
generals-1.0.0.dist-info/LICENSE
generals-1.0.0.dist-info/METADATA
generals-1.0.0.dist-info/WHEEL
generals-1.0.0.dist-info/top_level.txt
generals-1.0.0.dist-info/RECORD
