Metadata-Version: 2.1
Name: generals
Version: 1.0.0
Summary: Generals.io environment compliant with PettingZoo API standard powered by Numpy.
Home-page: https://github.com/strakam/Generals-RL
Author: Matej Straka
Author-email: strakammm@gmail.com
Classifier: Programming Language :: Python :: 3
Classifier: License :: OSI Approved :: MIT License
Requires-Python: >=3.11
License-File: LICENSE
Requires-Dist: numpy>=2.1.1
Requires-Dist: pettingzoo>=1.24.3
Requires-Dist: gymnasium>=0.29.1
Requires-Dist: mypy>=1.11.2
Requires-Dist: pre-commit>=3.2.2
Requires-Dist: pydantic>=2.9.1
Requires-Dist: pygame>=2.6.0
Requires-Dist: pytest>=8.3.3
Requires-Dist: scipy>=1.14.1
Requires-Dist: types-setuptools>=75.1.0.20240917
Requires-Dist: typing-extensions>=4.12.2
